ytclip/__init__.py
ytclip/cmd.py
ytclip/getremoteversion.py
ytclip/version.py
ytclip/ytclip.py
ytclip-1.2.11.dist-info/LICENSE
ytclip-1.2.11.dist-info/METADATA
ytclip-1.2.11.dist-info/WHEEL
ytclip-1.2.11.dist-info/entry_points.txt
ytclip-1.2.11.dist-info/top_level.txt
ytclip-1.2.11.dist-info/RECORD
