Metadata-Version: 2.1
Name: ytclip
Version: 1.2.11
Summary: Command to download a video and cut out a clip.
Home-page: https://github.com/zackees/ytclip
Author: Zach Vorhies
Author-email: dont@email.me
License: MIT
Classifier: License :: OSI Approved :: MIT License
Classifier: Programming Language :: Python :: 3.6
Classifier: Programming Language :: Python :: 3.9
Classifier: Operating System :: Microsoft :: Windows
Classifier: Operating System :: POSIX
Classifier: Operating System :: MacOS :: MacOS X
Classifier: Environment :: Console
Requires-Python: >=3.6.0
License-File: LICENSE
Requires-Dist: static-ffmpeg
Requires-Dist: yt-dlp >=2024.8.6
Requires-Dist: ytdlp-brighteon >=2023.10.3
Provides-Extra: test
Requires-Dist: pytest ; extra == 'test'
